salix_jmespath_tools/__init__.py
salix_jmespath_tools/customfunctions.py
salix_jmespath_tools/jmespathtypes.py
salix_jmespath_tools-0.2.0.dist-info/WHEEL
salix_jmespath_tools-0.2.0.dist-info/METADATA
salix_jmespath_tools-0.2.0.dist-info/RECORD
