Metadata-Version: 2.1
Name: salix-jmespath-tools
Version: 0.2.0
Summary: Custom functions for jmespath
License: MIT
Author: Salix
Author-email: salix@pilae.net
Requires-Python: >=3.7,<4.0
Classifier: License :: OSI Approved :: MIT License
Classifier: Programming Language :: Python :: 3
Classifier: Programming Language :: Python :: 3.10
Classifier: Programming Language :: Python :: 3.7
Classifier: Programming Language :: Python :: 3.8
Classifier: Programming Language :: Python :: 3.9
Requires-Dist: jmespath (>=1.0.0,<2.0.0)
